AUTHORS
LICENSE
MANIFEST.in
README.rst
requirements.txt
setup.py
js_test_tool/__init__.py
js_test_tool/browser.py
js_test_tool/coverage.py
js_test_tool/coverage_report.py
js_test_tool/dev_runner.py
js_test_tool/result_report.py
js_test_tool/runner.py
js_test_tool/suite.py
js_test_tool/suite_server.py
js_test_tool/tool.py
js_test_tool/util.py
js_test_tool.egg-info/PKG-INFO
js_test_tool.egg-info/SOURCES.txt
js_test_tool.egg-info/dependency_links.txt
js_test_tool.egg-info/entry_points.txt
js_test_tool.egg-info/requires.txt
js_test_tool.egg-info/top_level.txt
js_test_tool/runner/jasmine/jasmine-html.js
js_test_tool/runner/jasmine/jasmine-json.js
js_test_tool/runner/jasmine/jasmine.css
js_test_tool/runner/jasmine/jasmine.js
js_test_tool/runner/jasmine_requirejs/jasmine-html.js
js_test_tool/runner/jasmine_requirejs/jasmine-jquery.js
js_test_tool/runner/jasmine_requirejs/jasmine-json.js
js_test_tool/runner/jasmine_requirejs/jasmine.css
js_test_tool/runner/jasmine_requirejs/jasmine.js
js_test_tool/runner/jasmine_requirejs/jquery.js
js_test_tool/runner/jasmine_requirejs/require.js
js_test_tool/templates/console_report.txt
js_test_tool/templates/console_report_browser.txt
js_test_tool/templates/coverage_html_report.html
js_test_tool/templates/coverage_xml_report.xml
js_test_tool/templates/default_test_suite.yml
js_test_tool/templates/jasmine_requirejs_test_runner.html
js_test_tool/templates/jasmine_test_runner.html
js_test_tool/templates/xunit_report.txt