Metadata-Version: 1.1
Name: js-test-tool
Version: 0.1.5
Summary: Run JavaScript test suites and collect coverage information.
Home-page: http://github.com/edx/js-test-tool
Author: edX
Author-email: UNKNOWN
License: UNKNOWN
Platform: UNKNOWN
Classifier: Development Status :: 3 - Alpha
Classifier: Environment :: Console
Classifier: Intended Audience :: Developers
Classifier: License :: OSI Approved :: GNU Affero General Public License v3
Classifier: Operating System :: OS Independent
Classifier: Programming Language :: Python
Classifier: Topic :: Software Development :: Testing
Classifier: Topic :: Software Development :: Quality Assurance
